protoparser_ng/__init__.py
protoparser_ng/parser.py
proto_parser_ng-1.0.1.dist-info/LICENSE
proto_parser_ng-1.0.1.dist-info/METADATA
proto_parser_ng-1.0.1.dist-info/WHEEL
proto_parser_ng-1.0.1.dist-info/top_level.txt
proto_parser_ng-1.0.1.dist-info/RECORD
