Metadata-Version: 2.1
Name: proto-parser-ng
Version: 1.0.1
Summary: A package for parsing proto3 files
Home-page: https://github.com/Aaqua-live/protoparser-ng
Author: avac74
Author-email: andre.cruz@aaqua.live
License: UNKNOWN
Platform: UNKNOWN
Classifier: Programming Language :: Python :: 3
Classifier: License :: OSI Approved :: Apache Software License
Classifier: Operating System :: OS Independent
Classifier: Topic :: Software Development :: Libraries :: Python Modules
License-File: LICENSE
Requires-Dist: lark-parser (>=0.8.6)
Requires-Dist: numpy (>=1.14.0)
